Affirmations/Affirm.py
Affirmations/AffirmationText.py
Affirmations/__init__.py
Affirmations-0.0.10.dist-info/LICENSE
Affirmations-0.0.10.dist-info/METADATA
Affirmations-0.0.10.dist-info/WHEEL
Affirmations-0.0.10.dist-info/top_level.txt
Affirmations-0.0.10.dist-info/RECORD
